fouriax/__init__.py
fouriax/freq.py
fouriax/perceptual.py
fouriax/pvc.py
fouriax/py.typed
fouriax/stft.py
fouriax/time.py
fouriax-0.1.4.dist-info/METADATA
fouriax-0.1.4.dist-info/WHEEL
fouriax-0.1.4.dist-info/RECORD
