Metadata-Version: 2.1
Name: fouriax
Version: 0.1.4
Summary: A jax port of auraloss
Home-page: https://mikesol.github.io/fouriax
License: MIT
Author: Mike Solomon
Author-email: mike120982@gmail.com
Requires-Python: >=3.8,<4.0
Classifier: Development Status :: 4 - Beta
Classifier: Intended Audience :: Developers
Classifier: License :: OSI Approved :: MIT License
Classifier: Operating System :: OS Independent
Classifier: Programming Language :: Python
Classifier: Programming Language :: Python :: 3
Classifier: Programming Language :: Python :: 3.8
Classifier: Programming Language :: Python :: 3.9
Classifier: Programming Language :: Python :: 3.10
Classifier: Programming Language :: Python :: 3.11
Classifier: Programming Language :: Python :: 3.12
Classifier: Programming Language :: Python :: 3.7
Classifier: Topic :: Software Development :: Libraries :: Python Modules
Classifier: Typing :: Typed
Requires-Dist: jax
Requires-Dist: jaxlib
Requires-Dist: librosa
Requires-Dist: numpy
Requires-Dist: optax (<0.1.8)
Requires-Dist: scipy
Project-URL: Documentation, https://mikesol.github.io/fouriax
Project-URL: Repository, https://github.com/mikesol/fouriax
